Metadata-Version: 2.1
Name: parcelfile
Version: 1.1.2
Summary: Parcel does file command manipulation within python projects
Author: @malachi196
Author-email: "@malachi196" <malachiaaronwilson@gmail.com>
Project-URL: Homepage, https://github.com/malachi196/Parcelfile
Classifier: Programming Language :: Python :: 3
Classifier: License :: OSI Approved :: MIT License
Classifier: Operating System :: OS Independent
Requires-Python: >=3.8
License-File: LICENSE
